bayfile/__init__.py
bayfile/main.py
bayfile-1.0.2.dist-info/LICENSE
bayfile-1.0.2.dist-info/METADATA
bayfile-1.0.2.dist-info/WHEEL
bayfile-1.0.2.dist-info/entry_points.txt
bayfile-1.0.2.dist-info/top_level.txt
bayfile-1.0.2.dist-info/RECORD
