Metadata-Version: 2.1
Name: bayfile
Version: 1.0.2
Summary: upload and download to bayfile server
Home-page: https://github.com/redevil1/bayfiles
Author: Jak Bin
License: UNKNOWN
Project-URL: Bug Tracker, https://github.com/redevil1/bayfiles/issues
Keywords: bayfiles,bayfiles-api,bayfiles-cli,anonymous,upload,anonfile,anonfile-api,anonfile-cli
Platform: UNKNOWN
Classifier: Programming Language :: Python :: 3.6
Classifier: License :: OSI Approved :: MIT License
Classifier: Natural Language :: English
Classifier: Operating System :: OS Independent
Requires-Python: >=3
Requires-Dist: tqdm
